data_wise_akshare_mcp_server/__init__.py
data_wise_akshare_mcp_server/executor.py
data_wise_akshare_mcp_server/main.py
data_wise_akshare_mcp_server/query.py
data_wise_akshare_mcp_server/scanner.py
data_wise_akshare_mcp_server/test_akshare.py
data_wise_akshare_mcp_server-1.0.0.dist-info/METADATA
data_wise_akshare_mcp_server-1.0.0.dist-info/WHEEL
data_wise_akshare_mcp_server-1.0.0.dist-info/entry_points.txt
data_wise_akshare_mcp_server-1.0.0.dist-info/licenses/LICENSE
data_wise_akshare_mcp_server-1.0.0.dist-info/RECORD
