Metadata-Version: 2.4
Name: data-wise-akshare-mcp-server
Version: 1.0.0
Summary: AkShare MCP Server - 提供 AkShare 金融数据接口的 MCP 服务
Project-URL: Homepage, https://github.com/datawisecenter/akshare-mcp-server
Project-URL: Repository, https://github.com/datawisecenter/akshare-mcp-server
Project-URL: Documentation, https://github.com/datawisecenter/akshare-mcp-server#readme
Author-email: DataWiseCenter <contact@datawisecenter.com>
License: MIT
License-File: LICENSE
Keywords: akshare,fastmcp,finance,fund,futures,mcp,stock
Classifier: Development Status :: 4 - Beta
Classifier: Intended Audience :: Developers
Classifier: License :: OSI Approved :: MIT License
Classifier: Operating System :: OS Independent
Classifier: Programming Language :: Python :: 3
Classifier: Programming Language :: Python :: 3.8
Classifier: Programming Language :: Python :: 3.9
Classifier: Programming Language :: Python :: 3.10
Classifier: Programming Language :: Python :: 3.11
Classifier: Programming Language :: Python :: 3.12
Classifier: Topic :: Software Development :: Libraries :: Python Modules
Requires-Python: >=3.8
Requires-Dist: akshare
Requires-Dist: fastmcp>=2.14.1
Provides-Extra: dev
Requires-Dist: pytest-asyncio>=0.21.0; extra == 'dev'
Requires-Dist: pytest>=7.0.0; extra == 'dev'
